README.md
setup.py
twitter/__init__.py
twitter/api.py
twitter/api_client.py
twitter/error_mangement.py
twitter/paths.py
twitter/utils.py
twitter/endpoints/__init__.py
twitter/endpoints/tweets/__init__.py
twitter/endpoints/tweets/api.py
twitter/endpoints/tweets/models.py
twitter/endpoints/users/__init__.py
twitter/endpoints/users/api.py
twitter/endpoints/users/friendship_models.py
twitter/endpoints/users/models.py
twitter/models/__init__.py
twitter/models/cursor.py
twitter/models/datetime.py
twitter/models/entities.py
twitter/models/geo.py
twitter/models/media.py
twitter_sdk.egg-info/PKG-INFO
twitter_sdk.egg-info/SOURCES.txt
twitter_sdk.egg-info/dependency_links.txt
twitter_sdk.egg-info/requires.txt
twitter_sdk.egg-info/top_level.txt